mybitnet/__init__.py
mybitnet/bitnet/__init__.py
mybitnet/bitnet/bitnet.py
mybitnet/bitnet/models/bit_llama/__init__.py
mybitnet/bitnet/models/bit_llama/modeling_bit_llama.py
mybitnet/bitnet/replace_linears.py
mybitnet-0.6.0.dist-info/LICENSE
mybitnet-0.6.0.dist-info/METADATA
mybitnet-0.6.0.dist-info/WHEEL
mybitnet-0.6.0.dist-info/RECORD
